bdtools/__init__.py
bdtools/klt.py
bdtools/klt_backup.py
bdtools/mask.py
bdtools/nan.py
bdtools/norm.py
bdtools/patch.py
bdtools/path.py
bdtools/piv.py
bdtools/skel.py
bdtools/models/__init__.py
bdtools/models/annotate.py
bdtools/models/augment.py
bdtools/models/metrics.py
bdtools/models/preprocess.py
bdtools/models/unet.py
bd_tools-0.3.17.dist-info/LICENSE
bd_tools-0.3.17.dist-info/METADATA
bd_tools-0.3.17.dist-info/WHEEL
bd_tools-0.3.17.dist-info/top_level.txt
bd_tools-0.3.17.dist-info/RECORD
