Metadata-Version: 2.2
Name: bd-tools
Version: 0.3.17
Summary: Collection of tools for recurring tasks
Author: Benoit Dehapiot
Author-email: b.dehapiot@gmail.com
License: GNU General Public License v3 (GPLv3)
Requires-Python: >=3.9
License-File: LICENSE
Requires-Dist: numpy~=1.24.0
Requires-Dist: scipy
Requires-Dist: scikit-image
Requires-Dist: joblib
Requires-Dist: numba
Dynamic: author
Dynamic: author-email
Dynamic: description
Dynamic: description-content-type
Dynamic: license
Dynamic: requires-dist
Dynamic: requires-python
Dynamic: summary
